healthywork/__init__.py
healthywork/app.py
healthywork/config.py
healthywork-1.6.2.dist-info/AUTHORS
healthywork-1.6.2.dist-info/METADATA
healthywork-1.6.2.dist-info/WHEEL
healthywork-1.6.2.dist-info/entry_points.txt
healthywork-1.6.2.dist-info/pbr.json
healthywork-1.6.2.dist-info/top_level.txt
healthywork-1.6.2.dist-info/RECORD
