Metadata-Version: 2.1
Name: healthywork
Version: 1.6.2
Summary: Work break reminder
Home-page: https://github.com/Fuermohao/Healthy-Work
Author: Singein Zhang
Author-email: singein@outlook.com
License: MIT
Platform: UNKNOWN
Classifier: Development Status :: 4 - Beta
Classifier: Environment :: Console
Classifier: Environment :: OpenStack
Classifier: Intended Audience :: Developers
Classifier: Intended Audience :: Information Technology
Classifier: License :: OSI Approved :: Apache Software License
Classifier: Operating System :: OS Independent
Classifier: Programming Language :: Python
